hfd-0.1.5.dist-info/METADATA
hfd-0.1.5.dist-info/WHEEL
hfd-0.1.5.dist-info/entry_points.txt
hfd/__init__.py
hfd/hfd.cpython-311-darwin.so
hfd-0.1.5.dist-info/RECORD
