Metadata-Version: 2.4
Name: hfd
Version: 0.1.5
Classifier: Development Status :: 3 - Alpha
Classifier: Intended Audience :: Developers
Classifier: Intended Audience :: Science/Research
Classifier: License :: OSI Approved :: MIT License
Classifier: Programming Language :: Python :: 3.7
Classifier: Programming Language :: Python :: 3.8
Classifier: Programming Language :: Python :: 3.9
Classifier: Programming Language :: Python :: 3.10
Classifier: Programming Language :: Python :: 3.11
Classifier: Programming Language :: Rust
Classifier: Topic :: Scientific/Engineering :: Artificial Intelligence
Summary: Fast HuggingFace model downloader
Keywords: huggingface,model,download,machine-learning,deep-learning
Author: Your Name <your.email@example.com>
Author-email: migu <migu@example.com>
Maintainer-email: migu <migu@example.com>
Requires-Python: >=3.7
Project-URL: Homepage, https://github.com/migu/hfd
Project-URL: Repository, https://github.com/migu/hfd
Project-URL: Documentation, https://github.com/migu/hfd
